{"_id":{"$oid":"63685b561161ea082a2ce852"},"title":"A moreninha","subtitle":"","isbn":"9788532654847","authors":["Joaquim Manuel de Macedo"],"synopsis":"Lançado em 1844, A Moreninha é considerado o primeiro romance de qualidade publicado no Brasil. A obra conta a história de amor – que atravessa anos - entre Augusto e Carolina (a Moreninha). O romance é marcado por um ritmo ágil, com a presença frequente de diálogos entre os personagens, provocando um sintomático dinamismo narrativo, que nos dá a impressão de que a história está acontecendo no ato da leitura. Outra questão importante a ser ressaltada é a idealização do amor puro, que nasce na infância e permanece apesar do tempo e das intempéries.","publisher":"Editora Vozes","year":{"$numberInt":"2017"},"location":"Brasil","language":"Português","page_count":{"$numberInt":"240"},"dimensions":{"height":"18","width":"11"},"genre":[{"$oid":"63685731fe4943fd4777be22"},{"$oid":"6362b0a756577bbcbd7b42bb"}],"key_words":["Romance","costumes","Rio de Janeiro","império","vida social","identidade","ilha dos amores","amor puro"],"createdAt":{"$date":{"$numberLong":"1667783510843"}},"updatedAt":{"$date":{"$numberLong":"1667783510843"}},"__v":{"$numberInt":"0"}}